ypds_helpers/__about__.py
ypds_helpers/__init__.py
ypds_helpers/data_handling.py
ypds_helpers/globals.py
ypds_helpers/helpers.py
ypds_helpers/models.py
ypds_helpers/plotting.py
ypds_helpers-0.0.3.dist-info/METADATA
ypds_helpers-0.0.3.dist-info/WHEEL
ypds_helpers-0.0.3.dist-info/licenses/LICENSE
ypds_helpers-0.0.3.dist-info/RECORD
